llmcollection/__init__.py
llmcollection/GPT.py
llmcollection/LLAMA.py
llmcollection/Mixtral.py
llmcollection-0.2.0.dist-info/METADATA
llmcollection-0.2.0.dist-info/WHEEL
llmcollection-0.2.0.dist-info/RECORD
